unquad/__init__.py
unquad/estimation/__init__.py
unquad/estimation/base.py
unquad/estimation/extreme_conformal.py
unquad/estimation/standard_conformal.py
unquad/estimation/weighted_conformal.py
unquad/strategy/__init__.py
unquad/strategy/base.py
unquad/strategy/bootstrap.py
unquad/strategy/cross_val.py
unquad/strategy/jackknife.py
unquad/strategy/split.py
unquad/utils/__init__.py
unquad/utils/data/__init__.py
unquad/utils/data/load.py
unquad/utils/data/generator/__init__.py
unquad/utils/data/generator/base.py
unquad/utils/data/generator/batch.py
unquad/utils/data/generator/online.py
unquad/utils/func/__init__.py
unquad/utils/func/decorator.py
unquad/utils/func/enums.py
unquad/utils/func/params.py
unquad/utils/stat/__init__.py
unquad/utils/stat/aggregation.py
unquad/utils/stat/extreme.py
unquad/utils/stat/metrics.py
unquad/utils/stat/statistical.py
unquad-0.8.5.dist-info/METADATA
unquad-0.8.5.dist-info/WHEEL
unquad-0.8.5.dist-info/licenses/LICENSE
unquad-0.8.5.dist-info/RECORD
